LICENSE
MANIFEST.in
README.md
setup.cfg
setup.py
django_generic_awards/__init__.py
django_generic_awards/actions.py
django_generic_awards/admin.py
django_generic_awards/apps.py
django_generic_awards/mixins.py
django_generic_awards/models.py
django_generic_awards/views.py
django_generic_awards.egg-info/PKG-INFO
django_generic_awards.egg-info/SOURCES.txt
django_generic_awards.egg-info/dependency_links.txt
django_generic_awards.egg-info/requires.txt
django_generic_awards.egg-info/top_level.txt
django_generic_awards/forms/__init__.py
django_generic_awards/forms/fields.py
django_generic_awards/forms/forms.py
django_generic_awards/migrations/0001_initial.py
django_generic_awards/migrations/0002_auto_20200724_0902.py
django_generic_awards/migrations/0003_auto_20200724_1409.py
django_generic_awards/migrations/0004_delete_awardablemodel_link.py
django_generic_awards/migrations/0005_auto_20200727_1320.py
django_generic_awards/migrations/0006_auto_20200728_0945.py
django_generic_awards/migrations/0007_imageattachment.py
django_generic_awards/migrations/0008_auto_20200728_1330.py
django_generic_awards/migrations/0009_auto_20200729_0845.py
django_generic_awards/migrations/0010_auto_20200729_1014.py
django_generic_awards/migrations/0011_auto_20200804_1029.py
django_generic_awards/migrations/__init__.py
django_generic_awards/templates/admin/award_confirmation.html
django_generic_awards/tests/__init__.py
django_generic_awards/tests/test_settings.py
django_generic_awards/tests/tests.py
django_generic_awards/tests/urls.py